[
	{
		"id": 1,
		"imagen": "assets/images/bumeran.jpg",
		"titulo": "KARMA por Annie",
		"tamaño": "5cm x 6 cm aprox.",
		"precio": "3000"
	},
	{
		"id": 2,
		"imagen": "assets/images/golondrina.jpg",
		"titulo": "GOLONDRINAS por Facu",
		"tamaño": "25cm x 25cm aprox.",
		"precio": "18000"
	},
	{
		"id": 3,
		"imagen": "assets/images/serpiente.jpg",
		"titulo": "SNAKE por Sofi",
		"tamaño": "10cm x 15cm aprox.",
		"precio": "8000"
	},
	{
		"id": 4,
		"imagen": "assets/images/gato.png",
		"titulo": "666 CAT por Annie",
		"tamaño": "15cm x 20cm aprox.",
		"precio": "10000"
	},
	{
		"id": 5,
		"imagen": "assets/images/mariposa.jpg",
		"titulo": "BUTTERFLY por Annie",
		"tamaño": "10cm x 10cm aprox.",
		"precio": "12000"
	},
	{
		"id": 6,
		"imagen": "assets/images/pantera.jpg",
		"titulo": "PANTERA por Facu",
		"tamaño": "15cm x 20cm aprox.",
		"precio": "15000"
	},
	{
		"id": 7,
		"imagen": "assets/images/inside.png",
		"titulo": "INSIDE por Sofi",
		"tamaño": "10cm x 10cm aprox.",
		"precio": "10000"
	},
	{
		"id": 8,
		"imagen": "assets/images/screaming.jpg",
		"titulo": "SCREAMING por Facu",
		"tamaño": "15cm x 20cm aprox.",
		"precio": "15000"
	}
]
